django_shell_extended/__init__.py
django_shell_extended/settings.py
django_shell_extended/management/__init__.py
django_shell_extended/management/commands/__init__.py
django_shell_extended/management/commands/sh.py
django_shell_extended-1.0.0.dist-info/METADATA
django_shell_extended-1.0.0.dist-info/WHEEL
django_shell_extended-1.0.0.dist-info/licenses/LICENSE
django_shell_extended-1.0.0.dist-info/RECORD
