Metadata-Version: 2.3
Name: django-shell-extended
Version: 1.0.0
Summary: An extended Django shell
Project-URL: Homepage, https://gitlab.com/software-design-public/django-sh
Project-URL: Issues, https://gitlab.com/software-design-public/django-sh/-/issues
Author-email: Julian Bürklin <jb@software-design.de>
License-File: LICENSE
Classifier: License :: OSI Approved :: MIT License
Classifier: Operating System :: OS Independent
Classifier: Programming Language :: Python :: 3
Requires-Python: >=3.6
Requires-Dist: ipython
